{
  "parent": "minecraft:recipes/root",
  "criteria": {
    "has_the_recipe": {
      "conditions": {
        "recipe": "neolith:forge/torch_with_forge_from_stick"
      },
      "trigger": "minecraft:recipe_unlocked"
    },
    "hasstick": {
      "conditions": {
        "items": [
          {
            "items": [
              "minecraft:stick"
            ]
          }
        ]
      },
      "trigger": "minecraft:inventory_changed"
    }
  },
  "requirements": [
    [
      "hasstick",
      "has_the_recipe"
    ]
  ],
  "rewards": {
    "recipes": [
      "neolith:forge/torch_with_forge_from_stick"
    ]
  },
  "sends_telemetry_event": true
}